{
    "name": "EvolutionExampleSchema",
    "version": 1337,
    "columns": [
        {
            "name": "id",
            "offset": 0,
            "length": 9,
            "dtype": "int",
            "alignment": "Right",
            "pad_symbol": "Whitespace",
            "is_nullable": false
        },
        {
            "name": "name",
            "offset": 9,
            "length": 32,
            "dtype": "str",
            "is_nullable": true
        },
        {
            "name": "city",
            "offset": 41,
            "length": 32,
            "dtype": "str",
            "alignment": "Right",
            "pad_symbol": "Whitespace",
            "is_nullable": false
        },
        {
            "name": "employed",
            "offset": 73,
            "length": 5,
            "dtype": "bool",
            "alignment": "Center",
            "pad_symbol": "Whitespace",
            "is_nullable": false
        },
        {
            "name": "rings",
            "offset": 78,
            "length": 10,
            "dtype": "int",
            "alignment": "Left",
            "pad_symbol": "Whitespace",
            "is_nullable": false
        },
        {
            "name": "pet_name",
            "offset": 88,
            "length": 20,
            "dtype": "str",
            "alignment": "Left",
            "pad_symbol": "Whitespace",
            "is_nullable": false
        }
    ]
}

